.flake8
.isort.cfg
.pylintrc
.travis.yml
.yapf
AUTHORS
ChangeLog
LICENSE
Makefile
Pipfile
Pipfile.lock
README.rst
development.txt
requirements.txt
setup.cfg
setup.py
docs/example.py
eebrightbox/__init__.py
eebrightbox/errors.py
eebrightbox/helpers.py
eebrightbox.egg-info/PKG-INFO
eebrightbox.egg-info/SOURCES.txt
eebrightbox.egg-info/dependency_links.txt
eebrightbox.egg-info/not-zip-safe
eebrightbox.egg-info/pbr.json
eebrightbox.egg-info/requires.txt
eebrightbox.egg-info/top_level.txt
eebrightbox/router/__init__.py
eebrightbox/router/brightbox2.py
eebrightbox/router/smarthub.py
tests/__init__.py
tests/eebrightbox/__init__.py
tests/eebrightbox/test_core.py
tests/eebrightbox/router/test_brightbox2.py
tests/eebrightbox/router/test_smarthub.py
tests/eebrightbox/router/responses/cgi_myNetwork.js
tests/eebrightbox/router/responses/devices.xml
tests/eebrightbox/router/responses/ssids.xml